{"paths":{},"types":[],"uuids":["00FYSiSL9NP65p7Eh9ZZSJ","01g1YxYyNOYIL0xM3Ow7gp","04FQkv4zVBk4N9Vql9i6yO","05mBtsKK1J/YhnPzXIlu2/","0aRU0OsIRNeY2GuNsidfCp","10HcbDPsJBjbOMe3NNEYv9","11iCaGOKtEOagc7K6NPHPV","12CdhHgSFGCokTU7OsufBv","12w70Tk3NJdKXrQoF+jhIJ","14jIZxAvNGtoH03WOagbT7","20mlLgs5ZE1azrnRu1o93I","327kkTkBtPh7fynnGIu6GE","3c0oT+/6ZPI44Lad9aHot7","45jALJajhGMrIIbCgCEmmX","45okdo6UtOkqC6Flwb6JnB","46+5t/PMtBA7PmeVmRWxzf","5eBlIGYjdIYLuDZ7H5OCIW","60JhEriW9FNa3U8hpH7FXG","65Rdl+uXNCurfuDbfU73yI","67tJzzlz9KKpWdif5HaVlt","68tsp96mFBloPfYmqVZzgo","6dJY6lDolK9qI11py74Ex2","71X1fsKDNG1JyVFfWtGxFf","80R3Yd56JDXL/bAsGn5vIU","80xHCAwlRJ/ZjIiOLvxEXn","8az7aLX25OOaFVeOo5iarL","91DqU5UyJKgoHT29TbMbX8","95n0+WBcJIorAhr5t+FPpT","9bjfj9OnNChIxgIf+EX1nN","9fQ94mwoZI47AT+gdcGP5e","aaZXZOJDBODphHn7NPcV+K","b2VpI7yQlPXYxoeu26MMyr","b8oJ7Ki5RDApveWkHVqJ3A","bew5ZGJuVM8JvmOAk2FoQL","bfvhzM+6xJ4q4kgKnj5Bj4","c2O1GSJXVMKK4P0kPrehy8","c5kqEKKOtLQpPloXEu6o7p","c7TYRD95ZG+rU5ORTDWhQV","ccNDgAlZ5Jb7SZKFjL09I5","cd62p/UsxGVbsOPDFcSqhO","d7yui1s0VC5b2EQPFRqRVx","d89aWFLIRJtaVKnRWMUCYb","ddgJbCAXNL+q61w8/68N4R","e3Zh71IBxNWZ4sXwzsWUxJ","ea0l2KkfVC841dwp294KRo","f4F3JRsmFHV6BEUO6Lm11O","f5rNqpwGVHkri5deVieEny","f54n5Y9/9Nb57dCH6xiefx","f7gKtgszpBBIBQNqBDgp5D","01T15/6QFFu7LOZh9OQdAK","02delMVqdBD70a/HSD99FK","02pG2aN7lNfZMPwzvOiRxk","12T6VwxfdDjYQTcKRFR1Dx","138U4nxTNEGaJtJMSOxx2g","2e+yhGjTpFNJmy3yVh//kO","39G/u0SdZB2p5SWTIiA5h3","44nSHUOPhBmpUF2i8/beT3","48wKeuIx5CZpQHrRAcGcgV","4bBIeM/7xMtYmMJUB+zCm3","4cF/T1XnFKPoSWTeILcs9B","5a1Q8jia1AVY6AFwTMQFwO","5frgRQTN9KB6c08hbqRMhC","62zVMYpVFCb7RHqgQ3BNHz","6460gm3GlOFpgacJPqtaus","685hzq/ZpBcrBwSyyiD5aJ","7acgprcPNMH4CWqXooo58n","7eLBu6FMFK6YieYWg5/8jH","81yDqrjDtF4aK1LCrPcCyB","86kLXY6JpPnrmFcxulkMMy","87yqNkJmdC4aplVf0OAl+e","8bF0AJel5IsrTL67ke1zJ0","8bhrhzrz5GlLlg7+qReOHc","8caYYy2DZHWKDakfDvMuIt","8dIvEmcaFNiZBfP3bmj+7V","92HzOYpGpI55P+XrsjXZm/","9bv5rcYyhHEJclmsPR1lr0","9e088ku/JBD5uFlnuddo1B","a2MjXRFdtLlYQ5ouAFv/+R","adu/ZkhnpGDKLlxDa67VW+","b1ZNnkf7VDeIzCqQN4WGwC","b1a1pGDIZGlYuOvaWEbVhA","b7baUrBwBAYbRRVdroCoSt","ba3Vi4lFBIfqbKcEdlqRku","c5TgdRdJxLpKwMMDF/L086","c5duhX9RZD6YCbFe2Fw/lj","c9AZ/GRlNGQqXe3llj43/O","c9gnsUv85PXpKf3KqNEjN0","cc2kIgk/pJG5exABqJW+mO","cc5+hog/xD65lAYHewkIJa","cfd+zD+dtIk7uftKTYbcxA","d2WhVqwmRA8ZUY1BovaYbs","daKNEuYk5KrLVhtU6S8YYO","e7USQ8SURGCIUvJGtwFl9Y","ecpdLyjvZBwrvm+cedCcQy","ecssoj4WFLloyXVVWLayDc","f068GHHDNFZa88B4+qBZyI","f2BhiMQ3ZG/aypz9tAxMIh","feaqG76QdJ5aqfKy17c7LT","fe4/2DqZFD0YXg7QyMd3kQ"],"scenes":{"db://assets/game.fire":19},"redirect":[50,0,93,0],"deps":["internal"],"packs":{"0da129d9e":[0,49,1,51,6,52,53,54,11,55,56,57,58,59,60,61,62,63,19,64,65,66,67,68,69,70,71,72,73,74,75,76,77,78,79,80,81,82,83,84,85,86,87,88,89,90,91,92,94,95,96,97,98],"0f38f11c2":[2,3,4,5,7,8,9,10,12,13,14,15,16,17,18,20,21,22,23,24,25,26,27,28,29,30,31,32,33,34,35,36,37,38,39,40,41,42,43,44,45,46,47,48]},"name":"main","importBase":"import","nativeBase":"native","debug":false,"isZip":false,"encrypted":false,"versions":{"import":["0da129d9e","ed83f","0f38f11c2","f559c"],"native":[0,"d8ef6",1,"5196f",2,"69457",3,"5db4f",4,"8c363",5,"904ff",6,"95ecd",7,"0d935",8,"c11e6",9,"485de",10,"d389b",11,"0fab9",12,"05afc",13,"e15f2",14,"608ef",15,"c206d",16,"4f40d",17,"116d0",18,"5ae60",20,"fc014",21,"c09f9",22,"464fc",23,"1e67c",24,"6c64e",25,"1d9e8",26,"e9c2b",27,"9c7c0",28,"1d9e8",29,"92efd",30,"d9933",31,"4f29a",32,"b5673",33,"eb4c3",34,"f2a78",35,"81779",36,"cb3c1",37,"bb50c",38,"5a00e",39,"165cb",40,"bf7e5",41,"26e40",42,"6cdd0",43,"ddb15",44,"62646",45,"cbcf5",46,"d1d28",47,"f35c5",48,"608ef"]}}